{"id":52386,"path":"Assets/_HoleMoney/Prefabs/Game/coin.prefab","assetBundleId":-1,"components":[{"type":1,"id":70718,"data":[0.5,0.400000005960464,-0.379999995231628,1,1,1,0,0,0,1]},{"type":2,"id":70720,"enabled":1,"class":46,"data":[0,13,70822,47,70824,24,70826,43,70724,24,70828]},{"type":44,"id":70722,"data":[45,58110,null,null,0,0,0,0.5,1,1]},{"type":2,"id":70724,"enabled":1,"class":43,"data":[]}],"children":[{"id":70828,"path":"Assets/_HoleMoney/Prefabs/Game/coin.prefab","assetBundleId":-1,"components":[{"type":1,"id":70830,"data":[0,0,0,1.14999997615814,1.14999997615814,1.14999997615814,0,0,0,1]},{"type":14,"id":70966,"data":[10,58108]},{"type":13,"id":70968,"data":[null,null,1,9,50154,[9,50154,9,50990],1,1,0,0,-1,-1,1,1,0,0,1,1]}],"children":[],"data":["Hidden",0,0,0,0]},{"id":70960,"path":"Assets/_HoleMoney/Prefabs/Game/coin.prefab","assetBundleId":-1,"components":[{"type":1,"id":70832,"data":[0,0,0,1.14999997615814,1.14999997615814,1.14999997615814,0,0,0,1]},{"type":47,"id":70824,"data":[48,52000,null,null,0,1,0,[],0]}],"children":[{"id":70970,"path":"Assets/_HoleMoney/Prefabs/Game/coin.prefab","assetBundleId":-1,"components":[{"type":1,"id":70962,"data":[0,0,0,1,1,1,0,0,0,1]},{"type":14,"id":71126,"data":[10,57352]},{"type":13,"id":70822,"data":[null,null,1,9,51004,[9,51004],1,1,0,0,-1,-1,1,1,0,0,1,1]}],"children":[],"data":["Cylinder",0,1,0,0]},{"id":70826,"path":"Assets/_HoleMoney/Prefabs/Game/coin.prefab","assetBundleId":-1,"components":[{"type":1,"id":70964,"data":[0,0,0,1,1,1,-0.707106828689575,0,0,0.707106828689575]},{"type":31,"id":70972,"data":[[0.300000011920929,0,0,[0,null,null,1,0,0],[3,null,null,1,0.150000005960464,0.25],[0,null,null,1,0,5],0,[0,null,null,1,0,0.5],[0,null,null,1,0,1],[0,null,null,1,0,1],0,[0,null,null,1,0,0],[0,null,null,1,0,0],[0,null,null,1,0,0],[0,null,null,-8.84873569215984e-38,7.77720647700273e-43,5.41869432227922e+23,7.38820602330617e-41,1,1,1,1],[0,null,null,1,0,0],1,null,null,1,0,1,1,10,1,0],[0,[1,null,[0,[[1,1,1,1,0],[1,1,1,1,1]],[[1,0],[1,1]]],0,0,5.41748375469938e+23,7.38820602330617e-41,-65605994545152,3.53127213009854e-43,-65605994545152,3.53127213009854e-43],0,1],[0,[1,null,[0,[[1,1,1,1,0],[1,1,1,1,1]],[[1,0],[1,1]]],0,0,5.41744340244672e+23,7.38820602330617e-41,-65606061654016,3.53127213009854e-43,-65606061654016,3.53127213009854e-43]],[1,[0,null,null,1,0,0],[0,null,null,1,0,0],[[[3,null,null,1,0,3],1,0,3,0.00999999977648258,0]]],[0,[0,null,null,1,0,0],[0,null,null,1,0,0],[0,null,null,1,0,0.785398185253143],0,0,1],[0,[0,null,null,1,0,0],[0,null,null,1,0,0],[0,null,null,1,0,0.785398185253143],0],[1,4,0,0,0,0,0.200000002980232,0,0,[0,null,null,1,0,1],1,38.8600006103516,5,0,0,0,0,null,null,null,null,null,null,0,0,1,0,360,0,0,[0,null,null,1,0,1],0.200000002980232,0,0,0,0,0,0,1,1,1],[0,[1,null,[0,0,0,1,0,0,0,1,1,1,0,0,0,0],1,0,0],[1,null,[0,0,0,1,0,0,0,1,1,1,0,0,0,0],1,0,0],[1,null,[0,0,0,1,0,0,0,1,1,1,0,0,0,0],1,0,0],0,0,1],[1,[1,null,[0,1,0,0,0,0,0,1,0,-2,-2,0,0,0],1,0,0],[1,null,[0,0,0,1,0,0,0,1,1,1,0,0,0,0],1,0,0],[1,null,[0,0,0,1,0,0,0,1,1,1,0,0,0,0],1,0,0],0],[0,0,0,1,1,1,[1,null,[0,0,0,1,0,0,0,1,1,1,0,0,0,0],0.999899983406067,0,0],[0,null,null,1,0,0],1,0,0,0,1,[null,null]],[0,[0,null,null,1,0,0],[0,null,null,1,0,0],[0,null,null,1,0,0],[0,null,null,1,0,0],[0,null,null,1,0,1],1,[0,null,null,1,0,0],[0,null,null,1,0,0],[0,null,null,1,0,0],[0,null,null,1,0,0],[0,null,null,1,0,0],[0,null,null,1,0,0]],[0,0,[0,null,null,1,0,1],[0,null,null,1,0,1],[0,null,null,1,0,1],0.5,1,1,0.5,2,2,[0,null,null,1,0,0],0,0,[1,null,[0,-1,0,2,0,0,0,1,1,2,0,0,0,0],1,0,0],[1,null,[0,-1,0,2,0,0,0,1,1,2,0,0,0,0],1,0,0],[1,null,[0,-1,0,2,0,0,0,1,1,2,0,0,0,0],1,0,0],[0,null,null,1,0,1],[0,null,null,1,0,0],[0,null,null,1,0,0]],[0,0,[0,null,null,1,0,0]],[0,[0,null,null,1,0,0],[0,null,null,1,0,0],[0,null,null,1,0,0],0,0],[0,[0,null,null,1,0,1],[0,null,null,1,0,1],[0,null,null,1,0,1],[0,null,null,1,0,1],0,0,0,[0,null,null,1,0,0],1,1],1,0]},{"type":32,"id":70974,"data":[1,9,50990,[9,50990],0,0,0,0,-1,-1,1,1,0,0,0,0,10,52228,1,4,0,4,0,2,0,0,1,0,0,0.5,0,0,0,null,null]}],"children":[],"data":["Particle System",0,1,0,0]}],"data":["coin",0,1,0,0]}],"data":["coin",0,1,0,0]}