{"id":53720,"path":".\\Library\\PackageCache\\com.unity.render-pipelines.core@14.0.11\\Runtime\\Debugging\\Prefabs\\Widgets\\DebugUIToggle.prefab","assetBundleId":-1,"components":[{"type":22,"id":53480,"data":[0.5,0.5,0,0,0,0,0,26,0,0,0,0,0,0,1,1,1,1]},{"type":5,"id":54150,"enabled":1,"class":67,"data":[59,54858,68,54860,29,54862,0.800000011920929,0.800000011920929,0.800000011920929,1,0.25,0.649999976158142,0.800000011920929,1]}],"children":[{"id":54156,"path":".\\Library\\PackageCache\\com.unity.render-pipelines.core@14.0.11\\Runtime\\Debugging\\Prefabs\\Widgets\\DebugUIToggle.prefab","assetBundleId":-1,"components":[{"type":22,"id":53722,"data":[0.5,1,0,0,0.5,1,0,0,0,0,0,0,0,0,1,1,1,1]},{"type":28,"id":54856,"data":[1]},{"type":25,"id":54858,"enabled":1,"class":59,"data":[[62,46382,16,0,0,1,40,3,0,0,0,0,1],"New Text",null,null,1,0.800000011920929,0.800000011920929,0.800000011920929,1,0,0,0,0,0]}],"children":[],"data":["Text",0,1,0,5]},{"id":54152,"path":".\\Library\\PackageCache\\com.unity.render-pipelines.core@14.0.11\\Runtime\\Debugging\\Prefabs\\Widgets\\DebugUIToggle.prefab","assetBundleId":-1,"components":[{"type":22,"id":53724,"data":[0.5,0.5,0.5,0,1,1,0,0,0,0,0,0,0,0,1,1,1,1]},{"type":25,"id":54860,"enabled":1,"class":68,"data":[1,29,54862,[[[]]],null,null,1,[0,0,null,null,null,null,null,null,null,null],0,[1,1,1,1,0.960784316062927,0.960784316062927,0.960784316062927,1,0.7843137383461,0.7843137383461,0.7843137383461,1,0.960784316062927,0.960784316062927,0.960784316062927,1,0.7843137383461,0.7843137383461,0.7843137383461,0.501960813999176,1,0.100000001490116],[null,null,null,null,null,null,null,null],["Normal","Highlighted","Pressed","Highlighted","Disabled"],1,29,55606]}],"children":[{"id":54864,"path":".\\Library\\PackageCache\\com.unity.render-pipelines.core@14.0.11\\Runtime\\Debugging\\Prefabs\\Widgets\\DebugUIToggle.prefab","assetBundleId":-1,"components":[{"type":22,"id":54154,"data":[0.5,0.5,0,1,0,1,20,20,15,-12,0,0,0,0,1,1,1,1]},{"type":28,"id":55604,"data":[1]},{"type":25,"id":55606,"enabled":1,"class":29,"data":[17,46500,1,0,1,4,1,1,0,0,1,null,null,1,1,1,1,1,1,0,0,0,0]}],"children":[{"id":55608,"path":".\\Library\\PackageCache\\com.unity.render-pipelines.core@14.0.11\\Runtime\\Debugging\\Prefabs\\Widgets\\DebugUIToggle.prefab","assetBundleId":-1,"components":[{"type":22,"id":54866,"data":[0.5,0.5,0.5,0.5,0.5,0.5,11,11,-1,0,0,0,0,0,1,1,1,1]},{"type":28,"id":56022,"data":[1]},{"type":25,"id":54862,"enabled":1,"class":29,"data":[17,46502,0,0,1,4,1,1,0,0,1,null,null,1,1,1,1,1,1,0,0,0,0]}],"children":[],"data":["Checkmark",0,1,0,5]}],"data":["Background",0,1,0,5]}],"data":["Toggle",0,1,0,5]}],"data":["DebugUIToggle",0,1,0,5]}